vmxai/__init__.py
vmxai/auth/api_key.py
vmxai/auth/provider.py
vmxai/client.py
vmxai/types.py
vm_x_ai_sdk-1.7.0.dist-info/METADATA
vm_x_ai_sdk-1.7.0.dist-info/WHEEL
vm_x_ai_sdk-1.7.0.dist-info/RECORD
